{"is_source_file": true, "format": "TypeScript/TSX", "description": "This file defines a React functional component named NavBar that renders a top navigation bar with an app title and a search input. It exports the component as default and uses props for its value and onChange handler.", "external_files": ["react"], "external_methods": [], "published": ["default export: NavBar"], "classes": [], "methods": [{"name": "NavBar", "description": "React functional component rendering a navigation bar with a search input."}], "calls": ["onChange", "e.target.value"], "search-terms": ["NavBar", "react", "search input", "top navigation", "TypeScript", "props", "JSX"], "state": 2, "file_id": 8, "knowledge_revision": 18, "git_revision": "", "ctags": [], "hash": "7868fd4ffca97e81dfc84479bc7e8036", "format-version": 4, "code-base-name": "web_frontend", "filename": "web_frontend/src/components/NavBar.tsx", "revision_history": [{"18": ""}]}